sql_judge/__init__.py
sql_judge/__main__.py
sql_judge/adapter.py
sql_judge/schema.py
sql_judge/serialized_adapter.py
sql_judge/util.py
sql_judge/validate.py
sql_judge/validation_entity.py
sql_judge/validation_test_util.py
sql_judge/export/__init__.py
sql_judge/export/cli.py
sql_judge/export/csv.py
sql_judge/parse_configuration/__init__.py
sql_judge/parse_configuration/adapter_builder.py
sql_judge/parse_configuration/build_configuration.py
sql_judge/parse_configuration/default_configuration.json
sql_judge/parse_configuration/schema_validations.py
sql_judge-0.2.0.dist-info/LICENSE.md
sql_judge-0.2.0.dist-info/METADATA
sql_judge-0.2.0.dist-info/WHEEL
sql_judge-0.2.0.dist-info/entry_points.txt
sql_judge-0.2.0.dist-info/top_level.txt
sql_judge-0.2.0.dist-info/RECORD
