Metadata-Version: 2.1
Name: sql-judge
Version: 0.2.0
Summary: Validate SQL database Schemas using Python
Home-page: UNKNOWN
Author: MxBromelia
License: UNKNOWN
Platform: UNKNOWN
Requires-Python: >=3.7
